Workbook

Sheet Overview
A1: Beiwe AWS Cost Worksheet
A3: Purpose
A4: A study-design / grant-budgeting estimate of the AWS cost to run Beiwe. Default scenario is the planned grant: ~20-25 patients with up to 90 days of monitoring each.
A5: Covers AWS infrastructure for data collection, storage, and query only — NOT personnel, devices, or analysis compute.
A7: Scenario
A8: 24/7 always-on production Beiwe deployment in AWS us-east-1.
A9: Includes the additive infrastructure from the feat/ut-setup branch:
A10: - DynamoDB upload-metadata index (S3 -> EventBridge -> SQS -> Lambda -> DynamoDB).
A11: - Dedicated VPC with NO NAT gateway (saves ~$35/mo vs. a private-subnet design).
A12: The nightly-pause scheduler is NOT applied here (it would reduce the compute lines); it is listed on Fixed Costs as an optional saving.
A14: Threshold-aware
A15: Beiwe's compute and database STEP UP as enrollment grows — they are not flat.
... A40: Pricing is us-east-1 on-demand list price as of the build date; verify before quoting.

Sheet Pricing
A1: AWS Unit Pricing — us-east-1 (N. Virginia)
A2: On-demand list prices. Verify against the AWS pricing pages before quoting; rates current as of the build date below. Changing a rate here updates every dependent formula in the workbook.
A4: Item | B4: Unit | C4: Rate (USD) | D4: Source / notes
A5: EC2 t3.medium (Linux, on-demand) | B5: $/hour | C5: 0.0416 | D5: EC2 on-demand
A6: EC2 t3.large (Linux, on-demand) | B6: $/hour | C6: 0.0832 | D6: EC2 on-demand
A7: EC2 m5.large (Linux, on-demand) | B7: $/hour | C7: 0.096 | D7: EC2 on-demand
A8: RDS db.m5.large (PostgreSQL, Single-AZ) | B8: $/hour | C8: 0.171 | D8: RDS PostgreSQL on-demand
A9: RDS db.m5.xlarge (PostgreSQL, Single-AZ) | B9: $/hour | C9: 0.342 | D9: RDS PostgreSQL on-demand
A10: RDS db.m5.2xlarge (PostgreSQL, Single-AZ) | B10: $/hour | C10: 0.684 | D10: RDS PostgreSQL on-demand
A11: RDS db.m5.4xlarge (PostgreSQL, Single-AZ) | B11: $/hour | C11: 1.368 | D11: RDS PostgreSQL on-demand
A12: RDS gp2 storage | B12: $/GB-month | C12: 0.115 | D12: RDS storage
A13: RDS backup storage (beyond free allocation) | B13: $/GB-month | C13: 0.095 | D13: Free up to 100% of provisioned storage
A14: Classic Load Balancer (hourly) | B14: $/hour | C14: 0.025 | D14: ELB Classic (~$18/mo)
A15: Classic LB data processed | B15: $/GB | C15: 0.008 | D15: ELB Classic
A16: EBS gp3 volume | B16: $/GB-month | C16: 0.08 | D16: EBS
... A30: CloudWatch logs + metrics (estimate) | B30: $/month | C30: 3 | D30: Rough fixed allowance
A32: Build date | B32: 2026-06-24

Sheet Inputs
A1: Inputs — edit the yellow cells
A2: Server capacity (workers, RDS size/class, web instances) is DERIVED from the patient count on the Scaling sheet — adjust the ratios there. Everything else recalculates from these values and the Pricing sheet.
A4: Input | B4: Value | C4: Unit | D4: Notes
A5: Number of enrolled patients | B5: 25 | C5: patients | D5: Default = the planned grant scenario (~20-25 patients). Drives derived server capacity (Scaling sheet).
A6: Months of data collection per patient | B6: 3 | C6: months | D6: Default = 90 days monitoring (the grant scenario). Storage accumulates over this period and is retained afterward.
A7: Chunked data generated per patient / month | B7: 0.381 | C7: GB/patient/month | D7: Sample anchor: ~13 MiB/day (see Sample Data). HIGHLY dependent on enabled streams — motion sensors (accel/gyro/magnetometer) were 95% of the sample.
A8: Raw-upload retention multiplier | B8: 1 | C8: x chunked | D8: Raw uploads are also kept on S3 (~1.0x the chunked volume; total ~2x chunked). Set to 0 if raw is deleted after processing.
A9: Fraction archived to Glacier Deep Archive | B9: 0 | C9: 0-1 | D9: Cold data can be archived (S3File tracks Glacier state). 0 = everything in S3 Standard.
A10: EBS root volume per server | B10: 20 | C10: GB | D10: Applied to web + 1 manager + worker instances.
A11: Raw uploads per patient / day | B11: 150 | C11: uploads/day | D11: Drives metadata-index, S3-request, and DB-growth costs. Estimate; small either way.
A12: Data egress (researcher downloads) / month | B12: 0 | C12: GB/month | D12: Participant data downloaded over the internet. First 100 GB/mo is free.
A13: Hours per month | B13: 730 | C13: hours | D13: Billing convention (365*24/12). Leave at 730 for always-on.
A14: Days per month | B14: 30.44 | C14: days | D14: 365.25/12. Converts per-day rates to per-month.
A15: DynamoDB writes per upload | B15: 5 | C15: writes | D15: Metadata-index Lambda: marker + per-stream rollup + study rollup + 2 latest-pointers.

Sheet Scaling
A1: Scaling & thresholds
A2: Beiwe's compute and database step up as enrollment grows. These ratios convert patient count into required capacity. Defaults are CONSERVATIVE rules of thumb — calibrate the flagged ones against production telemetry (queue lag, DB size, CPU).
A4: Assumption | B4: Value | C4: Unit | D4: Notes
A5: Patients the manager alone keeps up with | B5: 150 | C5: patients | D5: Manager (t3.medium) also runs RabbitMQ + celery beat, so less than a dedicated worker. Below this, 0 workers needed. CALIBRATE with queue-lag metrics.
A6: Additional patients per worker box | B6: 250 | C6: patients/worker | D6: Each m5.large worker runs ~6 concurrent tasks (2*vCPU+2). 6-min cycle; tasks expire at 5:30, so the batch must drain in time. Processing is NOT auto-scaled — workers are added by hand. CALIBRATE.
A7: Patients per web instance | B7: 2500 | C7: patients/instance | D7: Upload endpoints are lightweight. ASG Max=2 today — beyond 2 instances, raise MaxSize. CALIBRATE.
A8: Minimum web instances | B8: 1 | C8: instances | D8: ASG MinSize.
A9: ChunkRegistry rows per patient / day | B9: 89 | C9: rows/day | D9: From sample (7,107 chunks / 8 patients / ~10 days). Stream-dependent.
A10: Bytes per DB row incl. indexes | B10: 0.8 | C10: KB/row | D10: ChunkRegistry + UploadTracking average. Rough.
A11: DB headroom / overhead factor | B11: 1.5 | C11: x | D11: Indexes, bloat, free space, and other tables (SummaryStatisticDaily, etc.).
A12: Workers => bump RDS to db.m5.xlarge | B12: 2 | C12: workers | D12: DB connection + CPU pressure: every web instance AND every celery process holds connections. db.m5.large ~= 830 max connections. CALIBRATE.
A13: Workers => bump RDS to db.m5.2xlarge | B13: 5 | C13: workers
A14: Workers => bump RDS to db.m5.4xlarge | B14: 11 | C14: workers
A16: Derived capacity for the current Inputs scenario
A17: Worker boxes required (m5.large) | B17: =ROUND(CEILING(MAX(0,Inputs!$B$5-Scaling!$B$5)/Scaling!$B$6,1),0)
A18: Web instances required | B18: =ROUND(MAX(Scaling!$B$8,CEILING(Inputs!$B$5/Scaling!$B$7,1)),0)
A19: RDS storage required (GB) | B19: =ROUND(MAX(50,ROUNDUP(Inputs!$B$5*Inputs!$B$6*(Scaling!$B$9+Inputs!$B$11)*Inputs!$B$14*Scaling!$B$10/1000000*Scaling!$B$11,0)),0)
A20: RDS instance class | B20: =IF(Scaling!$B$17>=Scaling!$B$14,"db.m5.4xlarge",IF(Scaling!$B$17>=Scaling!$B$13,"db.m5.2xlarge",IF(Scaling!$B$17>=Scaling!$B$12,"db.m5.xlarge","db.m5.large")))
A21: RDS instance rate ($/hr) | B21: =IF(Scaling!$B$17>=Scaling!$B$14,Pricing!$C$11,IF(Scaling!$B$17>=Scaling!$B$13,Pricing!$C$10,IF(Scaling!$B$17>=Scaling!$B$12,Pricing!$C$9,Pricing!$C$8)))
A23: Where the step-functions are
A24: Component | B24: What pushes it | C24: Action at threshold
A25: Processing workers | B25: Files per 6-min cycle (patients x upload cadence). ~6 concurrent tasks/m5.large; tasks expire at 5:30. NOT auto-scaled — added manually. | C25: Add m5.large workers
A26: RDS storage | B26: ChunkRegistry (~1 row/chunk) + UploadTracking (~1 row/upload) grow without bound; flagged 'very large on production' in CLAUDE.md. | C26: Raise allocation; gp2 gives only 3 IOPS/GB -> maybe gp3/io1
A27: RDS instance class | B27: DB connections + query CPU from web instances and every celery process. db.m5.large ~830 max connections. | C27: Step to xlarge / 2xlarge / 4xlarge
A28: Web tier | B28: Mobile upload request rate. ASG Max=2 today. | C28: Raise MaxSize / instance size
A29: RabbitMQ (on manager) | B29: Queue backlog held in manager RAM (4 GB) if processing lags. | C29: Bigger manager or dedicated broker
A30: S3 / DynamoDB / CLB | B30: Effectively unbounded. DDB is on-demand (auto-scales); per-study hot-partition is mitigated by the WRITE_STUDY_ROLLUP toggle. CLB auto-scales. | C30: Nothing (genuinely linear)

Sheet Savings Plan
A1: Savings Plan / Reserved Instance picker
A2: Pick a commitment in the yellow cell below. Savings Plans (EC2) and Reserved Instances (RDS) discount COMPUTE only — the EC2 servers and the RDS database instance. Storage (S3, EBS, RDS storage), the load balancer, DynamoDB, and data transfer always bill on-demand. Discount %s are approximate us-east-1 list values — overwrite them with a real quote from the AWS calculator or your account rep.
A4: Selected plan: | B4: None (on-demand)
A5: EC2 / compute discount applied | B5: =VLOOKUP($B$4,$A$9:$C$13,2,FALSE)
A6: RDS discount applied | B6: =VLOOKUP($B$4,$A$9:$C$13,3,FALSE)
A8: Plan | B8: EC2 / Compute SP discount | C8: RDS RI discount | D8: Term / payment
A9: None (on-demand) | B9: 0 | C9: 0 | D9: No commitment
A10: 1-year, no upfront | B10: 0.27 | C10: 0.3 | D10: 1 yr, $0 upfront
A11: 1-year, all upfront | B11: 0.3 | C11: 0.34 | D11: 1 yr, paid upfront
A12: 3-year, no upfront | B12: 0.45 | C12: 0.48 | D12: 3 yr, $0 upfront
A13: 3-year, all upfront | B13: 0.5 | C13: 0.53 | D13: 3 yr, paid upfront
A15: Compute savings at the current Inputs scenario
A16: On-demand compute (EC2 + RDS) / mo | B16: =((Scaling!$B$18+1)*Pricing!$C$5*Inputs!$B$13+Scaling!$B$17*Pricing!$C$7*Inputs!$B$13)+(Scaling!$B$21*Inputs!$B$13)
A17: With selected plan / mo | B17: =((Scaling!$B$18+1)*Pricing!$C$5*Inputs!$B$13+Scaling!$B$17*Pricing!$C$7*Inputs!$B$13)*(1-$B$5)+(Scaling!$B$21*Inputs!$B$13)*(1-$B$6)
A18: Monthly savings | B18: =B16-B17
A19: Annual savings | B19: =B18*12
A20: Effective discount on compute | B20: =IFERROR(B18/B16,0)
A22: Note: Savings Plans and RDS Reserved Instances are separate commitments; shown together here for convenience. Lambda is also SP-eligible but immaterial.

Sheet Fixed Costs
A1: Fixed / fixed-ish monthly costs (step up with patient count via the Scaling sheet)
A3: Component | B3: Detail | C3: Qty | D3: Unit cost basis | E3: Monthly cost | F3: Notes
A4: EB web tier | B4: t3.medium x web instances (derived) | C4: =Scaling!$B$18 | D4: instances x t3.medium/hr x hrs | E4: =Scaling!$B$18*Pricing!$C$5*Inputs!$B$13*(1-'Savings Plan'!$B$5) | F4: Derived from patients (Scaling). Autoscales; raise MaxSize beyond 2. Savings Plan applies.
A5: Classic Load Balancer | B5: 1 CLB | C5: 1 | D5: CLB/hr x hrs | E5: =1*Pricing!$C$14*Inputs!$B$13 | F5: Always running. + $0.008/GB processed (not modelled; small). NOT Savings-Plan eligible.
A6: Processing manager | B6: t3.medium x 1 | C6: 1 | D6: 1 x t3.medium/hr x hrs | E6: =1*Pricing!$C$5*Inputs!$B$13*(1-'Savings Plan'!$B$5) | F6: Celery + RabbitMQ broker run here (no separate broker cost). Savings Plan applies.
A7: Processing workers | B7: m5.large x workers (derived) | C7: =Scaling!$B$17 | D7: workers x m5.large/hr x hrs | E7: =Scaling!$B$17*Pricing!$C$7*Inputs!$B$13*(1-'Savings Plan'!$B$5) | F7: Derived from patients (Scaling). NOT auto-scaled in Beiwe — manual provisioning. Savings Plan applies.
A8: RDS instance | B8: class derived from workers | C8: =Scaling!$B$20 | D8: chosen class/hr x hrs | E8: =Scaling!$B$21*Inputs!$B$13*(1-'Savings Plan'!$B$6) | F8: Steps large->xlarge->2xlarge->4xlarge as load grows. RDS Reserved Instance discount applies.
A9: RDS storage | B9: gp2 (derived from DB growth) | C9: =Scaling!$B$19 | D9: GB x $/GB-mo | E9: =Scaling!$B$19*Pricing!$C$12 | F9: Grows with ChunkRegistry + UploadTracking. Min 50 GB.
A10: RDS backups | B10: 35-day retention | C10: 0 | D10: GB beyond free x $/GB-mo | E10: =0*Pricing!$C$13 | F10: Free up to 100% of provisioned storage. Set qty>0 if backup volume exceeds that.
A11: EBS volumes | B11: root volumes (web + mgr + workers) | C11: =(Scaling!$B$18+1+Scaling!$B$17)*Inputs!$B$10 | D11: total GB x $/GB-mo | E11: =(Scaling!$B$18+1+Scaling!$B$17)*Inputs!$B$10*Pricing!$C$16 | F11: Root disks for EC2 instances (RDS storage counted separately).
A12: Secrets Manager | B12: deploy credentials | C12: 1 | D12: secrets x $/secret-mo | E12: =1*Pricing!$C$28 | F12: beiwe-deploy-credentials (prerequisites stack).
A13: Route 53 | B13: 1 hosted zone | C13: 1 | D13: zone x $/mo | E13: =1*Pricing!$C$29 | F13: Domain hosting (if used).
A14: CloudWatch | B14: logs + metrics | C14: 1 | D14: estimate | E14: =1*Pricing!$C$30 | F14: Rough allowance incl. metadata-index Lambda logs/metrics.
A15: Metadata index (idle baseline) | B15: DynamoDB + SQS + Lambda + EventBridge | C15: 1 | D15: pay-per-request | E15: =0 | F15: Cost $0 when idle; usage-based cost is in Per-Patient Costs.
A16: Nightly pause scheduler | B16: EventBridge Scheduler + Lambda | C16: 1 | D16: optional | E16: =0 | F16: feat/ut-setup option; negligible to run. Would REDUCE compute lines if enabled. Not applied in this always-on model.
A17: FIXED MONTHLY SUBTOTAL | E17: =SUM(E4:E16)

Sheet Per-Patient Costs
A1: Per-patient (variable) monthly costs
A2: These scale linearly with patients (no step-functions). Storage is cumulative: the figures are the recurring monthly bill for the FULL dataset once all patients have completed collection (the steady-state peak).
A4: Derived dataset totals
A5: Total chunked data stored (GB) | B5: =Inputs!$B$5*Inputs!$B$6*Inputs!$B$7
A6: Total raw uploads stored (GB) | B6: =B5*Inputs!$B$8
A7: Total S3 data stored (GB) | B7: =B5+B6
A8: ... in Glacier Deep Archive (GB) | B8: =B7*Inputs!$B$9
A9: ... in S3 Standard (GB) | B9: =B7-B8
A10: Raw uploads per month (all patients) | B10: =Inputs!$B$5*Inputs!$B$11*Inputs!$B$14
A12: Component | B12: Basis | C12: Monthly cost | D12: Notes
A13: S3 storage — Standard | B13: standard GB x $/GB-mo | C13: =B9*Pricing!$C$17 | D13: Raw + chunked, compressed. The dominant per-patient cost.
A14: S3 storage — Glacier Deep Archive | B14: archived GB x $/GB-mo | C14: =B8*Pricing!$C$18 | D14: Only if a fraction is archived (Inputs).
A15: S3 PUT requests | B15: uploads x 2 (raw + chunk write) | C15: =B10*2/1000*Pricing!$C$19 | D15: Raw upload write + processed chunk write per upload.
A16: S3 GET requests | B16: uploads x 1 (processing reads) | C16: =B10*1/1000*Pricing!$C$20 | D16: Processing pipeline reads. Tiny.
A17: DynamoDB metadata index — writes | B17: uploads x writes/upload x $/M WRU | C17: =B10*Inputs!$B$15/1000000*Pricing!$C$21 | D17: 5 writes/upload (Inputs). On-demand.
A18: DynamoDB metadata index — storage | B18: 90-day marker retention | C18: =Inputs!$B$5*Inputs!$B$11*90*0.0000003*Pricing!$C$23 | D18: ~0.3 KB/marker, TTL 90 days, + small rollups. Negligible.
A19: SQS (metadata index) | B19: max(0, msgs - 1M free) x $/M | C19: =MAX(0,B10-1000000)/1000000*Pricing!$C$26 | D19: 1 message/upload; first 1M/mo free.
A20: Lambda (metadata index) | B20: invocations (batches of 10) + GB-sec | C20: =(B10/10/1000000*Pricing!$C$24)+(B10/10*0.256*0.2*Pricing!$C$25) | D20: 256 MB, ~0.2 s/batch of 10. Mostly free-tier.
A21: Data egress | B21: max(0, GB - 100 free) x $/GB | C21: =MAX(0,Inputs!$B$12-100)*Pricing!$C$27 | D21: Researcher downloads of participant data.
A22: PER-PATIENT MONTHLY SUBTOTAL (full dataset) | C22: =SUM(C13:C21)
A23: Per patient, per month of participation | C23: =C22/Inputs!$B$5/Inputs!$B$6

Sheet Totals
A1: Total cost summary (current Inputs scenario)
A2: Always-on production in us-east-1, including the metadata-index layer. Server capacity is derived from the patient count; see the Tiers sheet for the step-ups.
A4: Fixed monthly costs (servers, LB, RDS, overhead) | B4: ='Fixed Costs'!E17
A5: Per-patient monthly costs (storage, requests, index) | B5: ='Per-Patient Costs'!C22
A6: TOTAL MONTHLY | B6: =B4+B5
A7: TOTAL ANNUAL | B7: =B6*12
A9: Number of patients | B9: =Inputs!$B$5
A10: Total cost per patient / month (all-in) | B10: =B6/Inputs!$B$5
A11: Variable cost per patient / month of participation | B11: ='Per-Patient Costs'!C23
A13: STUDY TOTAL — collection period
A14: Months of data collection | B14: =Inputs!$B$6
A15: Approx. total to run the platform for the study | B15: =B6*Inputs!$B$6
A16: Approx. total per patient (whole study) | B16: =B15/Inputs!$B$5
A17: Storage-only cost/mo after collection (retention) | B17: ='Per-Patient Costs'!C22
A19: Includes: AWS infrastructure for data collection, storage, and query only.
A20: Excludes: personnel, participant devices/incentives, and analysis compute.
A21: Fixed infrastructure runs continuously and dominates at this scale; after collection ends you can pause/downsize servers and retain data cheaply (S3 / Glacier).
A22: Pricing is us-east-1 on-demand list price as of the Pricing-sheet build date — a dynamic estimate, not a fixed quote.

Sheet Tiers
A1: Cost by patient tier — where the step-ups happen
A2: Each column recomputes the full stack from its patient count, using the same Scaling ratios, Pricing, and per-patient assumptions. Edit the patient counts in row 4. Watch Workers and the RDS class/storage step up across the columns. The 25-patient column is the planned grant scenario.
A4: Enrolled patients | B4: 25 | C4: 100 | D4: 500 | E4: 1000 | F4: 5000 | G4: 25000
A5: Derived capacity
A6: Worker boxes (m5.large) | B6: =ROUND(CEILING(MAX(0,B$4-Scaling!$B$5)/Scaling!$B$6,1),0) | C6: =ROUND(CEILING(MAX(0,C$4-Scaling!$B$5)/Scaling!$B$6,1),0) | D6: =ROUND(CEILING(MAX(0,D$4-Scaling!$B$5)/Scaling!$B$6,1),0) | E6: =ROUND(CEILING(MAX(0,E$4-Scaling!$B$5)/Scaling!$B$6,1),0) | F6: =ROUND(CEILING(MAX(0,F$4-Scaling!$B$5)/Scaling!$B$6,1),0) | G6: =ROUND(CEILING(MAX(0,G$4-Scaling!$B$5)/Scaling!$B$6,1),0)
A7: Web instances | B7: =ROUND(MAX(Scaling!$B$8,CEILING(B$4/Scaling!$B$7,1)),0) | C7: =ROUND(MAX(Scaling!$B$8,CEILING(C$4/Scaling!$B$7,1)),0) | D7: =ROUND(MAX(Scaling!$B$8,CEILING(D$4/Scaling!$B$7,1)),0) | E7: =ROUND(MAX(Scaling!$B$8,CEILING(E$4/Scaling!$B$7,1)),0) | F7: =ROUND(MAX(Scaling!$B$8,CEILING(F$4/Scaling!$B$7,1)),0) | G7: =ROUND(MAX(Scaling!$B$8,CEILING(G$4/Scaling!$B$7,1)),0)
A8: RDS storage (GB) | B8: =ROUND(MAX(50,ROUNDUP(B$4*Inputs!$B$6*(Scaling!$B$9+Inputs!$B$11)*Inputs!$B$14*Scaling!$B$10/1000000*Scaling!$B$11,0)),0) | C8: =ROUND(MAX(50,ROUNDUP(C$4*Inputs!$B$6*(Scaling!$B$9+Inputs!$B$11)*Inputs!$B$14*Scaling!$B$10/1000000*Scaling!$B$11,0)),0) | D8: =ROUND(MAX(50,ROUNDUP(D$4*Inputs!$B$6*(Scaling!$B$9+Inputs!$B$11)*Inputs!$B$14*Scaling!$B$10/1000000*Scaling!$B$11,0)),0) | E8: =ROUND(MAX(50,ROUNDUP(E$4*Inputs!$B$6*(Scaling!$B$9+Inputs!$B$11)*Inputs!$B$14*Scaling!$B$10/1000000*Scaling!$B$11,0)),0) | F8: =ROUND(MAX(50,ROUNDUP(F$4*Inputs!$B$6*(Scaling!$B$9+Inputs!$B$11)*Inputs!$B$14*Scaling!$B$10/1000000*Scaling!$B$11,0)),0) | G8: =ROUND(MAX(50,ROUNDUP(G$4*Inputs!$B$6*(Scaling!$B$9+Inputs!$B$11)*Inputs!$B$14*Scaling!$B$10/1000000*Scaling!$B$11,0)),0)
A9: RDS instance class | B9: =IF(B$6>=Scaling!$B$14,"db.m5.4xlarge",IF(B$6>=Scaling!$B$13,"db.m5.2xlarge",IF(B$6>=Scaling!$B$12,"db.m5.xlarge","db.m5.large"))) | C9: =IF(C$6>=Scaling!$B$14,"db.m5.4xlarge",IF(C$6>=Scaling!$B$13,"db.m5.2xlarge",IF(C$6>=Scaling!$B$12,"db.m5.xlarge","db.m5.large"))) | D9: =IF(D$6>=Scaling!$B$14,"db.m5.4xlarge",IF(D$6>=Scaling!$B$13,"db.m5.2xlarge",IF(D$6>=Scaling!$B$12,"db.m5.xlarge","db.m5.large"))) | E9: =IF(E$6>=Scaling!$B$14,"db.m5.4xlarge",IF(E$6>=Scaling!$B$13,"db.m5.2xlarge",IF(E$6>=Scaling!$B$12,"db.m5.xlarge","db.m5.large"))) | F9: =IF(F$6>=Scaling!$B$14,"db.m5.4xlarge",IF(F$6>=Scaling!$B$13,"db.m5.2xlarge",IF(F$6>=Scaling!$B$12,"db.m5.xlarge","db.m5.large"))) | G9: =IF(G$6>=Scaling!$B$14,"db.m5.4xlarge",IF(G$6>=Scaling!$B$13,"db.m5.2xlarge",IF(G$6>=Scaling!$B$12,"db.m5.xlarge","db.m5.large")))
A10: Fixed monthly cost
A11: EB web tier | B11: =B$7*Pricing!$C$5*Inputs!$B$13*(1-'Savings Plan'!$B$5) | C11: =C$7*Pricing!$C$5*Inputs!$B$13*(1-'Savings Plan'!$B$5) | D11: =D$7*Pricing!$C$5*Inputs!$B$13*(1-'Savings Plan'!$B$5) | E11: =E$7*Pricing!$C$5*Inputs!$B$13*(1-'Savings Plan'!$B$5) | F11: =F$7*Pricing!$C$5*Inputs!$B$13*(1-'Savings Plan'!$B$5) | G11: =G$7*Pricing!$C$5*Inputs!$B$13*(1-'Savings Plan'!$B$5)
A12: Classic Load Balancer | B12: =Pricing!$C$14*Inputs!$B$13 | C12: =Pricing!$C$14*Inputs!$B$13 | D12: =Pricing!$C$14*Inputs!$B$13 | E12: =Pricing!$C$14*Inputs!$B$13 | F12: =Pricing!$C$14*Inputs!$B$13 | G12: =Pricing!$C$14*Inputs!$B$13
A13: Processing manager | B13: =Pricing!$C$5*Inputs!$B$13*(1-'Savings Plan'!$B$5) | C13: =Pricing!$C$5*Inputs!$B$13*(1-'Savings Plan'!$B$5) | D13: =Pricing!$C$5*Inputs!$B$13*(1-'Savings Plan'!$B$5) | E13: =Pricing!$C$5*Inputs!$B$13*(1-'Savings Plan'!$B$5) | F13: =Pricing!$C$5*Inputs!$B$13*(1-'Savings Plan'!$B$5) | G13: =Pricing!$C$5*Inputs!$B$13*(1-'Savings Plan'!$B$5)
A14: Processing workers | B14: =B$6*Pricing!$C$7*Inputs!$B$13*(1-'Savings Plan'!$B$5) | C14: =C$6*Pricing!$C$7*Inputs!$B$13*(1-'Savings Plan'!$B$5) | D14: =D$6*Pricing!$C$7*Inputs!$B$13*(1-'Savings Plan'!$B$5) | E14: =E$6*Pricing!$C$7*Inputs!$B$13*(1-'Savings Plan'!$B$5) | F14: =F$6*Pricing!$C$7*Inputs!$B$13*(1-'Savings Plan'!$B$5) | G14: =G$6*Pricing!$C$7*Inputs!$B$13*(1-'Savings Plan'!$B$5)
A15: RDS instance | B15: =(IF(B$6>=Scaling!$B$14,Pricing!$C$11,IF(B$6>=Scaling!$B$13,Pricing!$C$10,IF(B$6>=Scaling!$B$12,Pricing!$C$9,Pricing!$C$8))))*Inputs!$B$13*(1-'Savings Plan'!$B$6) | C15: =(IF(C$6>=Scaling!$B$14,Pricing!$C$11,IF(C$6>=Scaling!$B$13,Pricing!$C$10,IF(C$6>=Scaling!$B$12,Pricing!$C$9,Pricing!$C$8))))*Inputs!$B$13*(1-'Savings Plan'!$B$6) | D15: =(IF(D$6>=Scaling!$B$14,Pricing!$C$11,IF(D$6>=Scaling!$B$13,Pricing!$C$10,IF(D$6>=Scaling!$B$12,Pricing!$C$9,Pricing!$C$8))))*Inputs!$B$13*(1-'Savings Plan'!$B$6) | E15: =(IF(E$6>=Scaling!$B$14,Pricing!$C$11,IF(E$6>=Scaling!$B$13,Pricing!$C$10,IF(E$6>=Scaling!$B$12,Pricing!$C$9,Pricing!$C$8))))*Inputs!$B$13*(1-'Savings Plan'!$B$6) | F15: =(IF(F$6>=Scaling!$B$14,Pricing!$C$11,IF(F$6>=Scaling!$B$13,Pricing!$C$10,IF(F$6>=Scaling!$B$12,Pricing!$C$9,Pricing!$C$8))))*Inputs!$B$13*(1-'Savings Plan'!$B$6) | G15: =(IF(G$6>=Scaling!$B$14,Pricing!$C$11,IF(G$6>=Scaling!$B$13,Pricing!$C$10,IF(G$6>=Scaling!$B$12,Pricing!$C$9,Pricing!$C$8))))*Inputs!$B$13*(1-'Savings Plan'!$B$6)
A16: RDS storage | B16: =B$8*Pricing!$C$12 | C16: =C$8*Pricing!$C$12 | D16: =D$8*Pricing!$C$12 | E16: =E$8*Pricing!$C$12 | F16: =F$8*Pricing!$C$12 | G16: =G$8*Pricing!$C$12
A17: EBS volumes | B17: =(B$7+1+B$6)*Inputs!$B$10*Pricing!$C$16 | C17: =(C$7+1+C$6)*Inputs!$B$10*Pricing!$C$16 | D17: =(D$7+1+D$6)*Inputs!$B$10*Pricing!$C$16 | E17: =(E$7+1+E$6)*Inputs!$B$10*Pricing!$C$16 | F17: =(F$7+1+F$6)*Inputs!$B$10*Pricing!$C$16 | G17: =(G$7+1+G$6)*Inputs!$B$10*Pricing!$C$16
A18: Overhead (Secrets, R53, CloudWatch) | B18: =Pricing!$C$28+Pricing!$C$29+Pricing!$C$30 | C18: =Pricing!$C$28+Pricing!$C$29+Pricing!$C$30 | D18: =Pricing!$C$28+Pricing!$C$29+Pricing!$C$30 | E18: =Pricing!$C$28+Pricing!$C$29+Pricing!$C$30 | F18: =Pricing!$C$28+Pricing!$C$29+Pricing!$C$30 | G18: =Pricing!$C$28+Pricing!$C$29+Pricing!$C$30
A19: Fixed subtotal | B19: =SUM(B11:B18) | C19: =SUM(C11:C18) | D19: =SUM(D11:D18) | E19: =SUM(E11:E18) | F19: =SUM(F11:F18) | G19: =SUM(G11:G18)
A20: Per-patient monthly cost (full dataset)
A21: S3 storage (std + glacier) | B21: =(B$4*Inputs!$B$6*Inputs!$B$7*(1+Inputs!$B$8))*(1-Inputs!$B$9)*Pricing!$C$17+(B$4*Inputs!$B$6*Inputs!$B$7*(1+Inputs!$B$8))*Inputs!$B$9*Pricing!$C$18 | C21: =(C$4*Inputs!$B$6*Inputs!$B$7*(1+Inputs!$B$8))*(1-Inputs!$B$9)*Pricing!$C$17+(C$4*Inputs!$B$6*Inputs!$B$7*(1+Inputs!$B$8))*Inputs!$B$9*Pricing!$C$18 | D21: =(D$4*Inputs!$B$6*Inputs!$B$7*(1+Inputs!$B$8))*(1-Inputs!$B$9)*Pricing!$C$17+(D$4*Inputs!$B$6*Inputs!$B$7*(1+Inputs!$B$8))*Inputs!$B$9*Pricing!$C$18 | E21: =(E$4*Inputs!$B$6*Inputs!$B$7*(1+Inputs!$B$8))*(1-Inputs!$B$9)*Pricing!$C$17+(E$4*Inputs!$B$6*Inputs!$B$7*(1+Inputs!$B$8))*Inputs!$B$9*Pricing!$C$18 | F21: =(F$4*Inputs!$B$6*Inputs!$B$7*(1+Inputs!$B$8))*(1-Inputs!$B$9)*Pricing!$C$17+(F$4*Inputs!$B$6*Inputs!$B$7*(1+Inputs!$B$8))*Inputs!$B$9*Pricing!$C$18 | G21: =(G$4*Inputs!$B$6*Inputs!$B$7*(1+Inputs!$B$8))*(1-Inputs!$B$9)*Pricing!$C$17+(G$4*Inputs!$B$6*Inputs!$B$7*(1+Inputs!$B$8))*Inputs!$B$9*Pricing!$C$18
A22: S3 requests | B22: =(B$4*Inputs!$B$11*Inputs!$B$14)*2/1000*Pricing!$C$19+(B$4*Inputs!$B$11*Inputs!$B$14)/1000*Pricing!$C$20 | C22: =(C$4*Inputs!$B$11*Inputs!$B$14)*2/1000*Pricing!$C$19+(C$4*Inputs!$B$11*Inputs!$B$14)/1000*Pricing!$C$20 | D22: =(D$4*Inputs!$B$11*Inputs!$B$14)*2/1000*Pricing!$C$19+(D$4*Inputs!$B$11*Inputs!$B$14)/1000*Pricing!$C$20 | E22: =(E$4*Inputs!$B$11*Inputs!$B$14)*2/1000*Pricing!$C$19+(E$4*Inputs!$B$11*Inputs!$B$14)/1000*Pricing!$C$20 | F22: =(F$4*Inputs!$B$11*Inputs!$B$14)*2/1000*Pricing!$C$19+(F$4*Inputs!$B$11*Inputs!$B$14)/1000*Pricing!$C$20 | G22: =(G$4*Inputs!$B$11*Inputs!$B$14)*2/1000*Pricing!$C$19+(G$4*Inputs!$B$11*Inputs!$B$14)/1000*Pricing!$C$20
A23: Metadata index (DDB+SQS+Lambda) | B23: =(B$4*Inputs!$B$11*Inputs!$B$14)*Inputs!$B$15/1000000*Pricing!$C$21+B$4*Inputs!$B$11*90*0.0000003*Pricing!$C$23+MAX(0,(B$4*Inputs!$B$11*Inputs!$B$14)-1000000)/1000000*Pricing!$C$26+((B$4*Inputs!$B$11*Inputs!$B$14)/10/1000000*Pricing!$C$24)+((B$4*Inputs!$B$11*Inputs!$B$14)/10*0.256*0.2*Pricing!$C$25) | C23: =(C$4*Inputs!$B$11*Inputs!$B$14)*Inputs!$B$15/1000000*Pricing!$C$21+C$4*Inputs!$B$11*90*0.0000003*Pricing!$C$23+MAX(0,(C$4*Inputs!$B$11*Inputs!$B$14)-1000000)/1000000*Pricing!$C$26+((C$4*Inputs!$B$11*Inputs!$B$14)/10/1000000*Pricing!$C$24)+((C$4*Inputs!$B$11*Inputs!$B$14)/10*0.256*0.2*Pricing!$C$25) | D23: =(D$4*Inputs!$B$11*Inputs!$B$14)*Inputs!$B$15/1000000*Pricing!$C$21+D$4*Inputs!$B$11*90*0.0000003*Pricing!$C$23+MAX(0,(D$4*Inputs!$B$11*Inputs!$B$14)-1000000)/1000000*Pricing!$C$26+((D$4*Inputs!$B$11*Inputs!$B$14)/10/1000000*Pricing!$C$24)+((D$4*Inputs!$B$11*Inputs!$B$14)/10*0.256*0.2*Pricing!$C$25) | E23: =(E$4*Inputs!$B$11*Inputs!$B$14)*Inputs!$B$15/1000000*Pricing!$C$21+E$4*Inputs!$B$11*90*0.0000003*Pricing!$C$23+MAX(0,(E$4*Inputs!$B$11*Inputs!$B$14)-1000000)/1000000*Pricing!$C$26+((E$4*Inputs!$B$11*Inputs!$B$14)/10/1000000*Pricing!$C$24)+((E$4*Inputs!$B$11*Inputs!$B$14)/10*0.256*0.2*Pricing!$C$25) | F23: =(F$4*Inputs!$B$11*Inputs!$B$14)*Inputs!$B$15/1000000*Pricing!$C$21+F$4*Inputs!$B$11*90*0.0000003*Pricing!$C$23+MAX(0,(F$4*Inputs!$B$11*Inputs!$B$14)-1000000)/1000000*Pricing!$C$26+((F$4*Inputs!$B$11*Inputs!$B$14)/10/1000000*Pricing!$C$24)+((F$4*Inputs!$B$11*Inputs!$B$14)/10*0.256*0.2*Pricing!$C$25) | G23: =(G$4*Inputs!$B$11*Inputs!$B$14)*Inputs!$B$15/1000000*Pricing!$C$21+G$4*Inputs!$B$11*90*0.0000003*Pricing!$C$23+MAX(0,(G$4*Inputs!$B$11*Inputs!$B$14)-1000000)/1000000*Pricing!$C$26+((G$4*Inputs!$B$11*Inputs!$B$14)/10/1000000*Pricing!$C$24)+((G$4*Inputs!$B$11*Inputs!$B$14)/10*0.256*0.2*Pricing!$C$25)
A24: Per-patient subtotal | B24: =SUM(B21:B23) | C24: =SUM(C21:C23) | D24: =SUM(D21:D23) | E24: =SUM(E21:E23) | F24: =SUM(F21:F23) | G24: =SUM(G21:G23)
A25: Totals
A26: TOTAL MONTHLY | B26: =B19+B24 | C26: =C19+C24 | D26: =D19+D24 | E26: =E19+E24 | F26: =F19+F24 | G26: =G19+G24
A27: TOTAL ANNUAL | B27: =B26*12 | C27: =C26*12 | D27: =D26*12 | E27: =E26*12 | F27: =F26*12 | G27: =G26*12
A28: All-in $ / patient / month | B28: =B26/B$4 | C28: =C26/C$4 | D28: =D26/D$4 | E28: =E26/E$4 | F28: =F26/F$4 | G28: =G26/G$4
A29: Note: egress assumed 0 here (see Per-Patient Costs sheet for egress).

Sheet Sample Data
A1: Storage anchor — measured sample datasets
A3: Source: s3://beiwe-data-kowalski-beiwe-rxjfjw9miockp1gzxa42gd2zikzdrd3ndrclz
A4: Prefix: CHUNKED_DATA/2grtzwKjSxi64uYkxqZASgxe/ (public Zenodo-style sample data)
A5: Measured 2026-06-24 via `aws s3 ls --recursive` (sizes are the compressed .zst bytes — the S3 billing basis).
A6: 8 patients, 7,107 objects, 1,117,493,665 bytes (1.041 GiB) total.
A7: Avg 133 MiB/patient over ~8-22 day active spans => ~13 MiB/patient/day.
A8: ~89 ChunkRegistry rows/patient/day (this anchors the DB-growth assumption on the Scaling sheet).
A9: This is CHUNKED (processed) data only. Raw uploads are added via the 'raw multiplier' input.
A10: Storage is dominated by motion sensors — a study without them would be far smaller.
A12: Per data stream (sample aggregate)
A13: Data stream | B13: Size (MiB) | C13: % of bytes
A14: accelerometer | B14: 582.4 | C14: 0.546
A15: gyro | B15: 274.2 | C15: 0.257
A16: magnetometer | B16: 155.3 | C16: 0.146
A17: devicemotion | B17: 28.9 | C17: 0.027
A18: gps | B18: 9.2 | C18: 0.009
A19: ios_log | B19: 8 | C19: 0.008
A20: bluetooth | B20: 4.1 | C20: 0.004
A21: wifi | B21: 2 | C21: 0.002
A22: app_log | B22: 1.3 | C22: 0.001
A23: power_state | B23: 0.3 | C23: 0
A24: reachability/texts/calls/identifiers/surveys | B24: 0.1 | C24: 0
